[
  {
    "content_id": 800414,
    "reference_id": 203245,
    "title": "Leis básicas",
    "media_type": "Text",
    "index_reference": "leis básicas",
    "language": "por",
    "content": "<p>Nas Escrituras, o único Deus verdadeiro é a autoridade suprema. As leis de Deus incluem comandos positivos e negativos. Duas leis principais resumem os comandos positivos:</p><ul><li><p>“Amarás o Senhor teu Deus de todo o teu coração, de toda a tua alma e de toda a tua força” (<a href=\"https://ref.ly/Deut6:5\">Deuteronômio 6.5</a>; <a href=\"https://ref.ly/Matt22:37\">Mateus 22.37</a>; <a href=\"https://ref.ly/Mark12:30\">Marcos 12.30</a>; <a href=\"https://ref.ly/Luke10:27\">Lucas 10.27</a>).</p></li><li><p>“Ame o seu próximo como a si mesmo” (<a href=\"https://ref.ly/Lev19:18\">Levítico 19.18</a>; <a href=\"https://ref.ly/Matt19:19\">Mateus 19.19</a>; <a href=\"https://ref.ly/Mark12:31\">Marcos 12.31</a>; <a href=\"https://ref.ly/Luke10:27\">Lucas 10.27</a>).</p></li></ul><p>Podemos ver essas duas leis nos mandamentos positivos dos Dez Mandamentos (<a href=\"https://ref.ly/Exod20:2-Exod20:17\">Êxodo 20.2–17</a>; <a href=\"https://ref.ly/Deut5:6-Deut5:21\">Deuteronômio 5.6–21</a>):</p><ul><li><p>“Lembre-se do dia de sábado”</p></li><li><p>&quot;Honra teu pai e tua mãe&quot;</p></li></ul><p>Os mandamentos negativos estabelecem uma fronteira entre o bem e o mal. Os dois primeiros dos Dez Mandamentos são fundamentais:</p><ul><li><p>“Não terás outros deuses diante de Mim” (<a href=\"https://ref.ly/Exod20:3\">Êxodo 20.3</a>).</p></li><li><p>“Não farás para ti um ídolo na forma de qualquer coisa... Não te curvarás diante deles nem os adorarás” (<a href=\"https://ref.ly/Exod20:4-Exod20:5\">Êxodo 20.4–5</a>).</p></li></ul><p>Essas ações proibidas contrariam o mandamento fundamental de amar a Deus.</p><p>Os livros dos profetas mostram que Deus usa essas leis para julgar as ações dos israelitas. Deus também as utiliza para julgar qualquer governante, grupo ou pessoa em qualquer tempo ou lugar. Aqueles que violam essas leis principais rejeitam o único Deus verdadeiro, o que leva ao julgamento divino e a desastres para os pecadores.</p><p><u>Seções para estudo complementar</u></p><p><a href=\"https://ref.ly/Exod20:2-Exod20:17\">Êxodo 20.2–17</a>; <a href=\"https://ref.ly/Lev19:18\">Levítico 19.18</a>; <a href=\"https://ref.ly/Deut5:6-Deut5:21\">Deuteronômio 5.6–21</a>; <a href=\"https://ref.ly/Deut6:5\">6.5</a>; <a href=\"https://ref.ly/Jer2:7-Jer2:13\">Jeremias 2.7–13</a>; <a href=\"https://ref.ly/Jer3:8-Jer3:11\">3.8–11</a>; <a href=\"https://ref.ly/Jer5:1-Jer5:9\">5.1–9</a>; <a href=\"https://ref.ly/Jer6:10-Jer6:21\">6.10–21</a>; <a href=\"https://ref.ly/Jer7:16-Jer7:29\">7.16–29</a>; <a href=\"https://ref.ly/Jer8:9-Jer8:13\">8.9–13</a>; <a href=\"https://ref.ly/Jer11:6-Jer11:14\">11.6–14</a>; <a href=\"https://ref.ly/Jer17:1-Jer17:4\">17.1–4</a>; <a href=\"https://ref.ly/Jer22:1-Jer22:9\">22.1–9</a>; <a href=\"https://ref.ly/Jer23:10-Jer23:12\">23.10–12</a>; <a href=\"https://ref.ly/Jer34:8-Jer34:20\">34.8–20</a>; <a href=\"https://ref.ly/Matt19:19\">Mateus 19.19</a>; <a href=\"https://ref.ly/Matt22:37\">22.37</a>; <a href=\"https://ref.ly/Mark12:30-Mark12:31\">Marcos 12.30–31</a>; <a href=\"https://ref.ly/Luke10:27\">Lucas 10.27</a>; <a href=\"https://ref.ly/1Cor13:13\">1 Coríntios 13.13.</a></p>",
    "associations": {
      "passage": [
        {
          "start_ref": "02020003",
          "start_ref_usfm": "EXO 20:3",
          "end_ref": "02020003",
          "end_ref_usfm": "EXO 20:3"
        },
        {
          "start_ref": "03019018",
          "start_ref_usfm": "LEV 19:18",
          "end_ref": "03019018",
          "end_ref_usfm": "LEV 19:18"
        },
        {
          "start_ref": "05006005",
          "start_ref_usfm": "DEU 6:5",
          "end_ref": "05006005",
          "end_ref_usfm": "DEU 6:5"
        },
        {
          "start_ref": "40019019",
          "start_ref_usfm": "MAT 19:19",
          "end_ref": "40019019",
          "end_ref_usfm": "MAT 19:19"
        },
        {
          "start_ref": "40022037",
          "start_ref_usfm": "MAT 22:37",
          "end_ref": "40022037",
          "end_ref_usfm": "MAT 22:37"
        },
        {
          "start_ref": "41012030",
          "start_ref_usfm": "MRK 12:30",
          "end_ref": "41012030",
          "end_ref_usfm": "MRK 12:30"
        },
        {
          "start_ref": "41012031",
          "start_ref_usfm": "MRK 12:31",
          "end_ref": "41012031",
          "end_ref_usfm": "MRK 12:31"
        },
        {
          "start_ref": "42010027",
          "start_ref_usfm": "LUK 10:27",
          "end_ref": "42010027",
          "end_ref_usfm": "LUK 10:27"
        },
        {
          "start_ref": "46013013",
          "start_ref_usfm": "1CO 13:13",
          "end_ref": "46013013",
          "end_ref_usfm": "1CO 13:13"
        },
        {
          "start_ref": "02020002",
          "start_ref_usfm": "EXO 20:2",
          "end_ref": "02020017",
          "end_ref_usfm": "EXO 20:17"
        },
        {
          "start_ref": "05005006",
          "start_ref_usfm": "DEU 5:6",
          "end_ref": "05005021",
          "end_ref_usfm": "DEU 5:21"
        },
        {
          "start_ref": "02020004",
          "start_ref_usfm": "EXO 20:4",
          "end_ref": "02020005",
          "end_ref_usfm": "EXO 20:5"
        },
        {
          "start_ref": "24022001",
          "start_ref_usfm": "JER 22:1",
          "end_ref": "24022009",
          "end_ref_usfm": "JER 22:9"
        },
        {
          "start_ref": "24017001",
          "start_ref_usfm": "JER 17:1",
          "end_ref": "24017004",
          "end_ref_usfm": "JER 17:4"
        },
        {
          "start_ref": "24002007",
          "start_ref_usfm": "JER 2:7",
          "end_ref": "24002013",
          "end_ref_usfm": "JER 2:13"
        },
        {
          "start_ref": "24003008",
          "start_ref_usfm": "JER 3:8",
          "end_ref": "24003011",
          "end_ref_usfm": "JER 3:11"
        },
        {
          "start_ref": "24005001",
          "start_ref_usfm": "JER 5:1",
          "end_ref": "24005009",
          "end_ref_usfm": "JER 5:9"
        },
        {
          "start_ref": "24006010",
          "start_ref_usfm": "JER 6:10",
          "end_ref": "24006021",
          "end_ref_usfm": "JER 6:21"
        },
        {
          "start_ref": "24007016",
          "start_ref_usfm": "JER 7:16",
          "end_ref": "24007029",
          "end_ref_usfm": "JER 7:29"
        },
        {
          "start_ref": "24008009",
          "start_ref_usfm": "JER 8:9",
          "end_ref": "24008013",
          "end_ref_usfm": "JER 8:13"
        },
        {
          "start_ref": "24011006",
          "start_ref_usfm": "JER 11:6",
          "end_ref": "24011014",
          "end_ref_usfm": "JER 11:14"
        },
        {
          "start_ref": "24023010",
          "start_ref_usfm": "JER 23:10",
          "end_ref": "24023012",
          "end_ref_usfm": "JER 23:12"
        },
        {
          "start_ref": "24034008",
          "start_ref_usfm": "JER 34:8",
          "end_ref": "24034020",
          "end_ref_usfm": "JER 34:20"
        },
        {
          "start_ref": "41012030",
          "start_ref_usfm": "MRK 12:30",
          "end_ref": "41012031",
          "end_ref_usfm": "MRK 12:31"
        }
      ],
      "resource": []
    }
  }
]