[
  {
    "content_id": 800393,
    "reference_id": 203224,
    "title": "Riqueza e pobreza na literatura de sabedoria",
    "media_type": "Text",
    "index_reference": "riqueza e pobreza na literatura de sabedoria",
    "language": "por",
    "content": "<p>Os ensinamentos nas Escrituras sobre riqueza e pobreza, especialmente na literatura de sabedoria, revelam uma verdade abrangente. Deus abençoa pessoas sábias com riqueza, o que torna os desafios da vida mais fáceis de enfrentar (<a href=\"https://ref.ly/Prov3:9-Prov3:10\">Provérbios 3.9–10</a>,<a href=\"https://ref.ly/Prov3:15-Prov3:16\">15–16</a>; <a href=\"https://ref.ly/Prov10:22\">10.22</a>; <a href=\"https://ref.ly/Prov10:15\">10.15</a>). Comportamento tolo, especialmente a preguiça, muitas vezes leva à pobreza (veja <a href=\"https://ref.ly/Prov10:4\">10.4</a>).</p><p>O livro de Provérbios reconhece que algumas pessoas más e tolas são ricas, mas nos lembra que essa riqueza não durará muito (<a href=\"https://ref.ly/Prov11:18\">Provérbios 11.18</a>; <a href=\"https://ref.ly/Prov13:11\">13.11</a>). A pobreza às vezes pode resultar de injustiça em vez de tolice (<a href=\"https://ref.ly/Prov13:23\">13.23</a>). A riqueza pode vir da injustiça e desonestidade (<a href=\"https://ref.ly/Prov16:8\">16.8</a>). Aqueles com riqueza precisam usá-la sabiamente, incluindo ser generosos com os necessitados (<a href=\"https://ref.ly/Prov28:27\">28.27</a>; <a href=\"https://ref.ly/Prov29:7\">29.7</a>,<a href=\"https://ref.ly/Prov29:14\">14</a>).</p><p>A riqueza tem benefícios limitados. Às vezes, ela cria problemas em vez de resolvê-los (<a href=\"https://ref.ly/Prov11:4\">Provérbios 11.4</a>; <a href=\"https://ref.ly/Prov13:8\">13.8</a>). A sabedoria pode ajudar de maneiras que a riqueza não consegue, tornando a sabedoria mais importante do que o dinheiro (<a href=\"https://ref.ly/Prov15:16-Prov15:17\">15.16–17</a>; <a href=\"https://ref.ly/Prov16:8\">16.8</a>,<a href=\"https://ref.ly/Prov16:16\">16</a>).</p><p>Deus frequentemente abençoa as pessoas que vivem para agradá-lo, provendo o que elas precisam. Quando isso acontece, essas pessoas podem ajudar os outros compartilhando o que receberam. Esse ato de dar aos outros é, em si, outra bênção de Deus. No entanto, as circunstâncias nem sempre são justas. Às vezes, a riqueza não vai para aqueles que a merecem (veja <a href=\"https://ref.ly/Eccl9:11\">Eclesiastes 9.11</a>). Ela nem sempre traz felicidade (veja <a href=\"https://ref.ly/Eccl2:17-Eccl2:23\">Eclesiastes 2.17–23</a>; <a href=\"https://ref.ly/Eccl5:10-Eccl5:17\">5.10–17</a>). Na verdade, o dinheiro pode prejudicar a fé (<a href=\"https://ref.ly/1Tim6:10\">1 Timóteo 6.10</a>; <a href=\"https://ref.ly/Jas2:1-Jas2:13\">Tiago 2.1–13</a>). Ao escolher entre viver para agradar a Deus e o dinheiro, as pessoas sábias escolherão viver para agradar a Deus.</p><p><u>Passagens para estudo complementar</u></p><p><a href=\"https://ref.ly/Deut6:10-Deut6:13\">Deuteronômio 6.10–13</a>; <a href=\"https://ref.ly/Deut8:10-Deut8:11\">8.10–11</a>; <a href=\"https://ref.ly/1Sam2:7\">1 Samuel 2.7</a>; <a href=\"https://ref.ly/Ps37:16\">Salmo 37.16</a>; <a href=\"https://ref.ly/Prov3:9-Prov3:10\">Provérbios 3.9–10</a>,<a href=\"https://ref.ly/Prov3:15-Prov3:16\">15–16</a>; <a href=\"https://ref.ly/Prov10:15\">10.15</a>,<a href=\"https://ref.ly/Prov10:22\">22</a>; <a href=\"https://ref.ly/Prov11:4\">11.4</a>,<a href=\"https://ref.ly/Prov11:18\">18</a>,<a href=\"https://ref.ly/Prov11:28\">28</a>; <a href=\"https://ref.ly/Prov13:8\">13.8</a>,<a href=\"https://ref.ly/Prov13:11\">11</a>; <a href=\"https://ref.ly/Prov14:24\">14.24</a>; <a href=\"https://ref.ly/Prov15:6\">15.6</a>,<a href=\"https://ref.ly/Prov15:16-Prov15:17\">16–17</a>; <a href=\"https://ref.ly/Prov16:8\">16.8</a>,<a href=\"https://ref.ly/Prov16:16\">16</a>; <a href=\"https://ref.ly/Prov23:4-Prov23:5\">23.4–5</a>; <a href=\"https://ref.ly/Prov28:27\">28.27</a>; <a href=\"https://ref.ly/Prov29:7\">29.7</a>,<a href=\"https://ref.ly/Prov29:14\">14</a>; <a href=\"https://ref.ly/Eccl5:10-Eccl5:17\">Eclesiastes 5.10–17</a>; <a href=\"https://ref.ly/1Tim6:10\">1 Timóteo 6.10</a></p>",
    "associations": {
      "passage": [
        {
          "start_ref": "09002007",
          "start_ref_usfm": "1SA 2:7",
          "end_ref": "09002007",
          "end_ref_usfm": "1SA 2:7"
        },
        {
          "start_ref": "19037016",
          "start_ref_usfm": "PSA 37:16",
          "end_ref": "19037016",
          "end_ref_usfm": "PSA 37:16"
        },
        {
          "start_ref": "20010004",
          "start_ref_usfm": "PRO 10:4",
          "end_ref": "20010004",
          "end_ref_usfm": "PRO 10:4"
        },
        {
          "start_ref": "20010015",
          "start_ref_usfm": "PRO 10:15",
          "end_ref": "20010015",
          "end_ref_usfm": "PRO 10:15"
        },
        {
          "start_ref": "20010022",
          "start_ref_usfm": "PRO 10:22",
          "end_ref": "20010022",
          "end_ref_usfm": "PRO 10:22"
        },
        {
          "start_ref": "20011004",
          "start_ref_usfm": "PRO 11:4",
          "end_ref": "20011004",
          "end_ref_usfm": "PRO 11:4"
        },
        {
          "start_ref": "20011018",
          "start_ref_usfm": "PRO 11:18",
          "end_ref": "20011018",
          "end_ref_usfm": "PRO 11:18"
        },
        {
          "start_ref": "20011028",
          "start_ref_usfm": "PRO 11:28",
          "end_ref": "20011028",
          "end_ref_usfm": "PRO 11:28"
        },
        {
          "start_ref": "20013008",
          "start_ref_usfm": "PRO 13:8",
          "end_ref": "20013008",
          "end_ref_usfm": "PRO 13:8"
        },
        {
          "start_ref": "20013011",
          "start_ref_usfm": "PRO 13:11",
          "end_ref": "20013011",
          "end_ref_usfm": "PRO 13:11"
        },
        {
          "start_ref": "20013023",
          "start_ref_usfm": "PRO 13:23",
          "end_ref": "20013023",
          "end_ref_usfm": "PRO 13:23"
        },
        {
          "start_ref": "20014024",
          "start_ref_usfm": "PRO 14:24",
          "end_ref": "20014024",
          "end_ref_usfm": "PRO 14:24"
        },
        {
          "start_ref": "20015006",
          "start_ref_usfm": "PRO 15:6",
          "end_ref": "20015006",
          "end_ref_usfm": "PRO 15:6"
        },
        {
          "start_ref": "20016008",
          "start_ref_usfm": "PRO 16:8",
          "end_ref": "20016008",
          "end_ref_usfm": "PRO 16:8"
        },
        {
          "start_ref": "20016016",
          "start_ref_usfm": "PRO 16:16",
          "end_ref": "20016016",
          "end_ref_usfm": "PRO 16:16"
        },
        {
          "start_ref": "20028027",
          "start_ref_usfm": "PRO 28:27",
          "end_ref": "20028027",
          "end_ref_usfm": "PRO 28:27"
        },
        {
          "start_ref": "20029007",
          "start_ref_usfm": "PRO 29:7",
          "end_ref": "20029007",
          "end_ref_usfm": "PRO 29:7"
        },
        {
          "start_ref": "20029014",
          "start_ref_usfm": "PRO 29:14",
          "end_ref": "20029014",
          "end_ref_usfm": "PRO 29:14"
        },
        {
          "start_ref": "21009011",
          "start_ref_usfm": "ECC 9:11",
          "end_ref": "21009011",
          "end_ref_usfm": "ECC 9:11"
        },
        {
          "start_ref": "54006010",
          "start_ref_usfm": "1TI 6:10",
          "end_ref": "54006010",
          "end_ref_usfm": "1TI 6:10"
        },
        {
          "start_ref": "20023004",
          "start_ref_usfm": "PRO 23:4",
          "end_ref": "20023005",
          "end_ref_usfm": "PRO 23:5"
        },
        {
          "start_ref": "20003009",
          "start_ref_usfm": "PRO 3:9",
          "end_ref": "20003010",
          "end_ref_usfm": "PRO 3:10"
        },
        {
          "start_ref": "59002001",
          "start_ref_usfm": "JAS 2:1",
          "end_ref": "59002013",
          "end_ref_usfm": "JAS 2:13"
        },
        {
          "start_ref": "20003015",
          "start_ref_usfm": "PRO 3:15",
          "end_ref": "20003016",
          "end_ref_usfm": "PRO 3:16"
        },
        {
          "start_ref": "20015016",
          "start_ref_usfm": "PRO 15:16",
          "end_ref": "20015017",
          "end_ref_usfm": "PRO 15:17"
        },
        {
          "start_ref": "21002017",
          "start_ref_usfm": "ECC 2:17",
          "end_ref": "21002023",
          "end_ref_usfm": "ECC 2:23"
        },
        {
          "start_ref": "21005010",
          "start_ref_usfm": "ECC 5:10",
          "end_ref": "21005017",
          "end_ref_usfm": "ECC 5:17"
        },
        {
          "start_ref": "05006010",
          "start_ref_usfm": "DEU 6:10",
          "end_ref": "05006013",
          "end_ref_usfm": "DEU 6:13"
        },
        {
          "start_ref": "05008010",
          "start_ref_usfm": "DEU 8:10",
          "end_ref": "05008011",
          "end_ref_usfm": "DEU 8:11"
        }
      ],
      "resource": []
    }
  }
]