[
  {
    "content_id": 800398,
    "reference_id": 203229,
    "title": "Tudo é “Ilusão”",
    "media_type": "Text",
    "index_reference": "tudo é “ilusão”",
    "language": "por",
    "content": "<p>Uma palavra-chave no livro de Eclesiastes é o termo hebraico <em>hebel.</em> Esta palavra significa &quot;vapor&quot;. Muitas vezes é traduzida como &quot;sem sentido&quot;. Ela captura a visão principal do Mestre sobre a vida neste mundo. O Mestre, também chamado de Qoheleth, é o principal orador no livro de Eclesiastes.</p><p>A palavra hebraica <em>hebel</em> significa fisicamente &quot;fôlego&quot; ou &quot;vapor&quot;. <em>Hebel</em> aparece setenta e oito vezes no Antigo Testamento, mas apenas três vezes refere-se claramente ao sentido físico (<a href=\"https://ref.ly/Ps62:9\">Salmo 62.9</a>; <a href=\"https://ref.ly/Prov21:6\">Provérbios 21.6</a>; <a href=\"https://ref.ly/Isa57:13\">Isaías 57.13</a>). Nas outras setenta e cinco instâncias, descreve metaforicamente o que é difícil de entender, fútil, sem sentido, ilusório, falso, temporário ou sem substância.</p><p>O termo frequentemente descreve a falta de substância, realidade e valor dos falsos deuses (<a href=\"https://ref.ly/Deut32:21\">Deuteronômio 32.21</a>; <a href=\"https://ref.ly/2Kgs17:15\">2 Reis 17.15</a>). Nesse sentido, <em>hebel</em> é o oposto de &quot;glória&quot;. A glória de Deus é sua presença que tem substância, é pesada e duradoura. Às vezes, <em>hebel</em> representa como a vida é curta e momentânea, como vapor (<a href=\"https://ref.ly/Job7:16\">Jó 7.16</a>; <a href=\"https://ref.ly/Ps144:4\">Salmo 144.4</a>). Em outros casos, refere-se a como a vida pode ser sem sentido e frustrante (<a href=\"https://ref.ly/Ps78:33\">Salmos 78.33</a>; <a href=\"https://ref.ly/Ps94:11\">94.11</a>; <a href=\"https://ref.ly/Isa49:4\">Isaías 49.4</a>).</p><p>Há uma longa tradição de interpretar <em>hebel</em> em Eclesiastes como significando &quot;vaidade&quot;. Isso não se refere a ter uma alta opinião de si mesmo, mas a experimentar a vida como vazia e sem propósito. A antiga tradução grega do Antigo Testamento usou a palavra <em>mataiotēs</em>, que significa &quot;vazio&quot; ou &quot;futilidade&quot;.</p><p>A Vulgata Latina traduziu <em>hebel</em> com a palavra latina <em>vanitas</em>, que significa &quot;sem propósito&quot;, &quot;oco&quot; ou &quot;sem valor&quot;. Da Vulgata vem a tradição de traduzir a palavra como &quot;vaidade&quot; em português. A maioria dos tradutores hoje entende <em>hebel</em> como significando que a vida na terra parece não ter um propósito ou significado claro, e tudo o que fazemos parece fútil.</p><p>Alguns tradutores interpretam <em>hebel</em> em Eclesiastes como referindo-se principalmente à natureza temporária da vida. Um vapor não tem permanência ou peso. Esta tradução sugere uma visão diferente de Eclesiastes. A vida não é sem sentido e fútil, mas sim não permanente e de rápida conclusão. Muitas frases em Eclesiastes insinuam a natureza passageira ou breve da vida humana e de seus esforços.</p><p>No Novo Testamento, uma ideia semelhante aparece em <a href=\"https://ref.ly/Jas4:13-Jas4:15\">Tiago 4.13–15</a>. Compreender <em>hebel</em> como &quot;não permanente&quot; em Eclesiastes ajuda a explicar o livro de forma clara. No entanto, é uma visão menos comum entre os estudiosos.</p><p>Ao ler Eclesiastes, lembre-se de que a raiz da palavra é &quot;fôlego&quot; ou &quot;vapor&quot;, o que apoia as metáforas. A brevidade e os desafios da vida podem parecer deprimentes. Isso deve nos encorajar a trabalhar arduamente e com sabedoria, e a aproveitar a vida enquanto possível. Todos nós já experimentamos eventos injustos na vida, como uma pessoa tola tendo sucesso ou injustiça não punida. Essas coisas fazem mais sentido quando lembramos que Deus está no controle. Deus julgará tudo o que fazemos, incluindo todos os segredos, sejam bons ou maus (<a href=\"https://ref.ly/Eccl12:14\">Eclesiastes 12.14</a>).</p><p><u>Passagens para estudo complementar</u></p><p><a href=\"https://ref.ly/Deut32:21\">Deuteronômio 32.21</a>; <a href=\"https://ref.ly/2Kgs17:15\">2 Reis 17.15</a>; <a href=\"https://ref.ly/Job7:16\">Jó 7.16</a>; <a href=\"https://ref.ly/Ps62:9\">Salmos 62.9</a>; <a href=\"https://ref.ly/Ps78:33\">78.33</a>; <a href=\"https://ref.ly/Ps94:11\">94.11</a>; <a href=\"https://ref.ly/Ps144:4\">144.4</a>; <a href=\"https://ref.ly/Prov21:6\">Provérbios 21.6</a>; <a href=\"https://ref.ly/Eccl1:2\">Eclesiastes 1.2</a>; <a href=\"https://ref.ly/Isa30:7\">Isaías 30.7</a>; <a href=\"https://ref.ly/Isa49:4\">49.4</a>; <a href=\"https://ref.ly/Isa57:13\">57.13</a></p>",
    "associations": {
      "passage": [
        {
          "start_ref": "05032021",
          "start_ref_usfm": "DEU 32:21",
          "end_ref": "05032021",
          "end_ref_usfm": "DEU 32:21"
        },
        {
          "start_ref": "12017015",
          "start_ref_usfm": "2KI 17:15",
          "end_ref": "12017015",
          "end_ref_usfm": "2KI 17:15"
        },
        {
          "start_ref": "18007016",
          "start_ref_usfm": "JOB 7:16",
          "end_ref": "18007016",
          "end_ref_usfm": "JOB 7:16"
        },
        {
          "start_ref": "19062009",
          "start_ref_usfm": "PSA 62:9",
          "end_ref": "19062009",
          "end_ref_usfm": "PSA 62:9"
        },
        {
          "start_ref": "19078033",
          "start_ref_usfm": "PSA 78:33",
          "end_ref": "19078033",
          "end_ref_usfm": "PSA 78:33"
        },
        {
          "start_ref": "19094011",
          "start_ref_usfm": "PSA 94:11",
          "end_ref": "19094011",
          "end_ref_usfm": "PSA 94:11"
        },
        {
          "start_ref": "19144004",
          "start_ref_usfm": "PSA 144:4",
          "end_ref": "19144004",
          "end_ref_usfm": "PSA 144:4"
        },
        {
          "start_ref": "20021006",
          "start_ref_usfm": "PRO 21:6",
          "end_ref": "20021006",
          "end_ref_usfm": "PRO 21:6"
        },
        {
          "start_ref": "21001002",
          "start_ref_usfm": "ECC 1:2",
          "end_ref": "21001002",
          "end_ref_usfm": "ECC 1:2"
        },
        {
          "start_ref": "21012014",
          "start_ref_usfm": "ECC 12:14",
          "end_ref": "21012014",
          "end_ref_usfm": "ECC 12:14"
        },
        {
          "start_ref": "23030007",
          "start_ref_usfm": "ISA 30:7",
          "end_ref": "23030007",
          "end_ref_usfm": "ISA 30:7"
        },
        {
          "start_ref": "23049004",
          "start_ref_usfm": "ISA 49:4",
          "end_ref": "23049004",
          "end_ref_usfm": "ISA 49:4"
        },
        {
          "start_ref": "23057013",
          "start_ref_usfm": "ISA 57:13",
          "end_ref": "23057013",
          "end_ref_usfm": "ISA 57:13"
        },
        {
          "start_ref": "59004013",
          "start_ref_usfm": "JAS 4:13",
          "end_ref": "59004015",
          "end_ref_usfm": "JAS 4:15"
        }
      ],
      "resource": []
    }
  }
]