[
  {
    "content_id": 734206,
    "reference_id": 203221,
    "title": "Le mariage et la sexualité",
    "media_type": "Text",
    "index_reference": "le mariage et la sexualité",
    "language": "fra",
    "content": "<p>La Bible traite le mariage comme quelque chose de sacré dès le commencement. La sexualité en est un élément important (<a href=\"https://ref.ly/Gen2:23-Gen2:25\">Gn 2.23–25</a>). Lorsque le péché entre dans le monde, toutes les relations humaines commencent à en souffrir. Cela se manifeste d&apos;abord dans la relation entre êtres humains et Dieu, puis entre mari et femme, et même entre êtres humains et création (<a href=\"https://ref.ly/Gen3:1-Gen3:24\">Genèse 3</a>). Le fait qu&apos;Adam et Ève ont désormais honte d&apos;être nus est un effet négatif de la chute sur leur sexualité.</p><p>Dans le livre des Proverbes, le maître sage avertit souvent les jeunes hommes d&apos;éviter les tentations sexuelles, c&apos;est-à-dire la sexualité en dehors du mariage (<a href=\"https://ref.ly/Prov2:16-Prov2:22\">Pr 2.16–22&nbsp;</a>; <a href=\"https://ref.ly/Prov5:1-Prov5:23\">5.1–23&nbsp;</a>; <a href=\"https://ref.ly/Prov6:20-Prov7:27\">6.20–7.27</a>). Bien qu&apos;un jeune homme puisse trouver d&apos;autres femmes attirantes, céder à ces tentations peut avoir de graves conséquences. Ses objectifs familiaux et professionnels pourraient s&apos;en trouver détruits. Les Proverbes recommandent aux jeunes hommes de trouver une femme de valeur, de lui être fidèle, et de chercher le plaisir sexuel en elle et elle seule (<a href=\"https://ref.ly/Prov5:15-Prov5:20\">Pr 5.15–20</a>).</p><p>Bien que cette section des Proverbes ait été écrite à l&apos;origine comme enseignement à de jeunes hommes, ce qui est enseigné à propos du mariage et de la sexualité est un enseignement valable pour tous. Le livre des Proverbes encourage chacun à reconnaître la sainteté et la beauté de l&apos;amour conjugal tel que Dieu, le sage Créateur, l&apos;a créé.</p><p>Le Nouveau Testament souligne aussi de diverses façons que la sexualité doit être pratiquée dans la sainteté et uniquement dans le cadre du mariage. Jésus rappelle l&apos;histoire de la création dans la Genèse pour démontrer la volonté de Dieu dès le commencement que le mariage soit une relation permanente et exclusive entre un homme et une femme. Après avoir cité <a href=\"https://ref.ly/Gen2:24\">Genèse 2.24</a>, Jésus dit : « <span>Ainsi ils ne sont plus deux, mais ils sont une seule chair. Que l’homme donc ne sépare pas ce que Dieu a joint</span> » (<a href=\"https://ref.ly/Matt19:3-Matt19:6\">Mt 19.3–6</a>). </p><p>L&apos;apôtre Paul parle de l&apos;importance de maintenir l&apos;intimité sexuelle dans le mariage pour éviter la tentation par Satan (<a href=\"https://ref.ly/1Cor7:3-1Cor7:5\">1Co 7.3–5</a>). Dieu veut que ceux qui se marient restent fidèles l&apos;un à l&apos;autre et ne se rendent pas coupables d&apos;activités sexuelles nuisibles (voir <a href=\"https://ref.ly/Heb13:4\">Hé 13.4</a>).</p><p><u>Passages pour une étude plus approfondie</u></p><p><a href=\"https://ref.ly/Gen2:18-Gen2:25\">Genèse 2.18–25</a> ; <a href=\"https://ref.ly/Prov2:16-Prov2:22\">Proverbes 2.16–22</a> ; <a href=\"https://ref.ly/Prov5:15-Prov5:20\">5.15–20</a> ; <a href=\"https://ref.ly/Prov6:20-Prov6:35\">6.20–35</a> ; <a href=\"https://ref.ly/Prov7:1-Prov7:27\">7.1–27</a> ; <a href=\"https://ref.ly/Jer5:7-Jer5:11\">Jérémie 5.7–11</a> ; <a href=\"https://ref.ly/Hos2:20\">Osée 2.22</a> ; <a href=\"https://ref.ly/Mal2:14-Mal2:16\">Malachie 2.14–16</a> ; <a href=\"https://ref.ly/Matt19:4-Matt19:6\">Matthieu 19.4–6</a> ; <a href=\"https://ref.ly/Matt22:30\">22.30</a> ; <a href=\"https://ref.ly/1Cor6:15-1Cor6:20\">1&nbsp;Corinthiens 6.15–20</a> ; <a href=\"https://ref.ly/Heb13:4\">Hébreux 13.4</a></p>",
    "associations": {
      "passage": [
        {
          "start_ref": "01002024",
          "start_ref_usfm": "GEN 2:24",
          "end_ref": "01002024",
          "end_ref_usfm": "GEN 2:24"
        },
        {
          "start_ref": "28002020",
          "start_ref_usfm": "HOS 2:20",
          "end_ref": "28002020",
          "end_ref_usfm": "HOS 2:20"
        },
        {
          "start_ref": "40022030",
          "start_ref_usfm": "MAT 22:30",
          "end_ref": "40022030",
          "end_ref_usfm": "MAT 22:30"
        },
        {
          "start_ref": "58013004",
          "start_ref_usfm": "HEB 13:4",
          "end_ref": "58013004",
          "end_ref_usfm": "HEB 13:4"
        },
        {
          "start_ref": "01003001",
          "start_ref_usfm": "GEN 3:1",
          "end_ref": "01003024",
          "end_ref_usfm": "GEN 3:24"
        },
        {
          "start_ref": "39002014",
          "start_ref_usfm": "MAL 2:14",
          "end_ref": "39002016",
          "end_ref_usfm": "MAL 2:16"
        },
        {
          "start_ref": "20005001",
          "start_ref_usfm": "PRO 5:1",
          "end_ref": "20005023",
          "end_ref_usfm": "PRO 5:23"
        },
        {
          "start_ref": "20006020",
          "start_ref_usfm": "PRO 6:20",
          "end_ref": "20006035",
          "end_ref_usfm": "PRO 6:35"
        },
        {
          "start_ref": "20007001",
          "start_ref_usfm": "PRO 7:1",
          "end_ref": "20007027",
          "end_ref_usfm": "PRO 7:27"
        },
        {
          "start_ref": "01002018",
          "start_ref_usfm": "GEN 2:18",
          "end_ref": "01002025",
          "end_ref_usfm": "GEN 2:25"
        },
        {
          "start_ref": "46006015",
          "start_ref_usfm": "1CO 6:15",
          "end_ref": "46006020",
          "end_ref_usfm": "1CO 6:20"
        },
        {
          "start_ref": "01002023",
          "start_ref_usfm": "GEN 2:23",
          "end_ref": "01002025",
          "end_ref_usfm": "GEN 2:25"
        },
        {
          "start_ref": "20002016",
          "start_ref_usfm": "PRO 2:16",
          "end_ref": "20002022",
          "end_ref_usfm": "PRO 2:22"
        },
        {
          "start_ref": "20006020",
          "start_ref_usfm": "PRO 6:20",
          "end_ref": "20007027",
          "end_ref_usfm": "PRO 7:27"
        },
        {
          "start_ref": "20005015",
          "start_ref_usfm": "PRO 5:15",
          "end_ref": "20005020",
          "end_ref_usfm": "PRO 5:20"
        },
        {
          "start_ref": "40019003",
          "start_ref_usfm": "MAT 19:3",
          "end_ref": "40019006",
          "end_ref_usfm": "MAT 19:6"
        },
        {
          "start_ref": "46007003",
          "start_ref_usfm": "1CO 7:3",
          "end_ref": "46007005",
          "end_ref_usfm": "1CO 7:5"
        },
        {
          "start_ref": "24005007",
          "start_ref_usfm": "JER 5:7",
          "end_ref": "24005011",
          "end_ref_usfm": "JER 5:11"
        },
        {
          "start_ref": "40019004",
          "start_ref_usfm": "MAT 19:4",
          "end_ref": "40019006",
          "end_ref_usfm": "MAT 19:6"
        }
      ],
      "resource": []
    }
  }
]