[
  {
    "content_id": 709598,
    "reference_id": 203369,
    "title": "नए अगुओं को अधिकार और ज़िम्मेदारी सौंपना",
    "media_type": "Text",
    "index_reference": "नए अगुओं को अधिकार और ज़िम्मेदारी सौंपना",
    "language": "hin",
    "content": "<p>एक मसीही अगुवे की भूमिका उन लोगों की सेवा करना और उनके लिए कठिनाइयों को सहना है जिनका वह मार्गदर्शन करता है  (<a href=\"https://ref.ly/Mark10:35-Mark10:45\">मर 10:35–45</a>)। प्रेरित पौलुस के लिए उत्तम अगुवाई का अर्थ यीशु मसीह के समान उदाहरण स्थापित करना था। यीशु की क्रूस पर मृत्यु, पौलुस के लिए सबसे महत्वपूर्ण बात थी और उसी ने उनके जीवन को पूरी तरह से आकार दिया। उन्होंने कहा, “मैं उसको और उसके पुनरुत्थान की सामर्थ्य को, और उसके साथ दुःखों में सहभागी होने के मर्म को जानूँ” (<a href=\"https://ref.ly/Phil3:10\">फिलि 3:10</a>; देखें <a href=\"https://ref.ly/Col1:24\">कुलु 1:24</a>)।</p><p>उनका अर्थ केवल भावनात्मक संघर्षों या पाप से निपटने से नहीं था। उसका आशय भयंकर शारीरिक पीड़ा का अनुभव करना था। पौलुस ने उन लोगों के लिए कठिनाइयों को सहन किया, जिनके साथ उन्होंने सुसमाचार बाँटा। उन्होंने हमेशा उनके उद्धार को अपनी सुरक्षा से अधिक प्राथमिकता दी (<a href=\"https://ref.ly/2Tim2:10\">2 तीमु 2:10</a>; <a href=\"https://ref.ly/2Cor4:8-2Cor4:12\">2 कुरि 4:8–12</a>)।</p><p>एक मसीही अगुवे का जीवन, दूसरों को यीशु की क्रूस पर मृत्यु के विषय में दर्शाता है। यह दिखाता है कि कैसे परमेश्वर निर्बल मनुष्यों के द्वारा भी शक्तिशाली तरीके से काम करते हैं (<a href=\"https://ref.ly/2Cor12:8-2Cor12:10\">2 कुरि 12:8–10</a>)। यह मानवीय मूर्खता के बावजूद परमेश्वर की बुद्धि को भी दर्शाता है (<a href=\"https://ref.ly/1Cor1:18-1Cor1:31\">1 कुरि 1:18–31</a>)। जब पौलुस ने प्रेरित तीमुथियुस को नेतृत्व करने के लिए बुलाया, तो उन्होंने उसे &quot;दुःख उठा&quot; ने के लिए भी कहा (<a href=\"https://ref.ly/2Tim4:1-2Tim4:5\">2 तीमु 4:1–5</a>; <a href=\"https://ref.ly/2Tim1:8\">1:8</a>; <a href=\"https://ref.ly/2Tim2:3\">2:3</a>; <a href=\"https://ref.ly/2Tim4:5\">4:5</a>)। पौलुस ने तीमुथियुस से कहा कि वह क्रूस से लज्जित न हों (<a href=\"https://ref.ly/2Tim1:8\">1:8</a>)।</p><p>सच्ची मसीही अगुवाई में यीशु मसीह के उस उदाहरण का पालन करना आवश्यक है जिसमें उन्होंने दूसरों को अपने से पहले रखा। जब अगुवे मसीह की जगह अपने ऊपर ध्यान केन्द्रित करते हैं, तो वे यीशु के सुसमाचार को अपने जीवन में नहीं जीते। एक अच्छा अगुवा यीशु के उदाहरण का अनुसरण करता है—दूसरों की सेवा और देखभाल करता है, न कि अपने लाभ की खोज करता है (देखें <a href=\"https://ref.ly/Phil2:3-Phil2:8\">फिलि 2:3–8</a>)। ये अगुवें कठिन समय का अनुभव करने के लिए तैयार हैं। वे जानते हैं कि जो लोग यीशु की मृत्यु में सहभागी होते हैं, वे उसके जीवन में भी सहभागी होंगे और जो लोग कठिनाइयों में विश्वासयोग्य बने रहते हैं, वे उसके साथ राज्य भी करेंगे (<a href=\"https://ref.ly/2Tim2:11-2Tim2:12\">2 तीमु 2:11–12</a>)।</p><p><u>अधिक अध्ययन के लिए अंश</u></p><p><a href=\"https://ref.ly/John13:15\">यूहन्ना 13:15</a>; <a href=\"https://ref.ly/Acts20:35\">प्रेरितों के काम 20:35</a>; <a href=\"https://ref.ly/2Cor4:8-2Cor4:12\">2 कुरिन्थियों 4:8–12</a>; <a href=\"https://ref.ly/Eph5:2\">इफिसियों 5:2</a>; <a href=\"https://ref.ly/Col1:24\">कुलुस्सियों 1:24</a>; <a href=\"https://ref.ly/1Thess1:6-1Thess1:7\">1 थिस्सलुनीकियों 1:6–7</a>; <a href=\"https://ref.ly/2Thess3:9\">2 थिस्सलुनीकियों 3:9</a>; <a href=\"https://ref.ly/1Tim1:16\">1 तीमुथियुस 1:16</a>; <a href=\"https://ref.ly/1Tim4:12\">4:12</a>; <a href=\"https://ref.ly/2Tim1:8\">2 तीमुथियुस 1:8</a>, <a href=\"https://ref.ly/2Tim1:12\">12</a>; <a href=\"https://ref.ly/2Tim2:3\">2:3</a>, <a href=\"https://ref.ly/2Tim2:10-2Tim2:12\">10–12</a>; <a href=\"https://ref.ly/2Tim4:1-2Tim4:5\">4:1–5</a>; <a href=\"https://ref.ly/Titus2:7\">तीतुस 2:7</a>; <a href=\"https://ref.ly/Heb6:12\">इब्रानियों 6:12</a>; <a href=\"https://ref.ly/Heb13:7\">13:7</a>; <a href=\"https://ref.ly/1Pet2:21\">1 पतरस 2:21</a>; <a href=\"https://ref.ly/1Pet5:1-1Pet5:4\">5:1–4</a></p>",
    "associations": {
      "passage": [
        {
          "start_ref": "43013015",
          "start_ref_usfm": "JHN 13:15",
          "end_ref": "43013015",
          "end_ref_usfm": "JHN 13:15"
        },
        {
          "start_ref": "44020035",
          "start_ref_usfm": "ACT 20:35",
          "end_ref": "44020035",
          "end_ref_usfm": "ACT 20:35"
        },
        {
          "start_ref": "49005002",
          "start_ref_usfm": "EPH 5:2",
          "end_ref": "49005002",
          "end_ref_usfm": "EPH 5:2"
        },
        {
          "start_ref": "50003010",
          "start_ref_usfm": "PHP 3:10",
          "end_ref": "50003010",
          "end_ref_usfm": "PHP 3:10"
        },
        {
          "start_ref": "51001024",
          "start_ref_usfm": "COL 1:24",
          "end_ref": "51001024",
          "end_ref_usfm": "COL 1:24"
        },
        {
          "start_ref": "53003009",
          "start_ref_usfm": "2TH 3:9",
          "end_ref": "53003009",
          "end_ref_usfm": "2TH 3:9"
        },
        {
          "start_ref": "54001016",
          "start_ref_usfm": "1TI 1:16",
          "end_ref": "54001016",
          "end_ref_usfm": "1TI 1:16"
        },
        {
          "start_ref": "54004012",
          "start_ref_usfm": "1TI 4:12",
          "end_ref": "54004012",
          "end_ref_usfm": "1TI 4:12"
        },
        {
          "start_ref": "55001008",
          "start_ref_usfm": "2TI 1:8",
          "end_ref": "55001008",
          "end_ref_usfm": "2TI 1:8"
        },
        {
          "start_ref": "55001012",
          "start_ref_usfm": "2TI 1:12",
          "end_ref": "55001012",
          "end_ref_usfm": "2TI 1:12"
        },
        {
          "start_ref": "55002003",
          "start_ref_usfm": "2TI 2:3",
          "end_ref": "55002003",
          "end_ref_usfm": "2TI 2:3"
        },
        {
          "start_ref": "55002010",
          "start_ref_usfm": "2TI 2:10",
          "end_ref": "55002010",
          "end_ref_usfm": "2TI 2:10"
        },
        {
          "start_ref": "55004005",
          "start_ref_usfm": "2TI 4:5",
          "end_ref": "55004005",
          "end_ref_usfm": "2TI 4:5"
        },
        {
          "start_ref": "56002007",
          "start_ref_usfm": "TIT 2:7",
          "end_ref": "56002007",
          "end_ref_usfm": "TIT 2:7"
        },
        {
          "start_ref": "58006012",
          "start_ref_usfm": "HEB 6:12",
          "end_ref": "58006012",
          "end_ref_usfm": "HEB 6:12"
        },
        {
          "start_ref": "58013007",
          "start_ref_usfm": "HEB 13:7",
          "end_ref": "58013007",
          "end_ref_usfm": "HEB 13:7"
        },
        {
          "start_ref": "60002021",
          "start_ref_usfm": "1PE 2:21",
          "end_ref": "60002021",
          "end_ref_usfm": "1PE 2:21"
        },
        {
          "start_ref": "41010035",
          "start_ref_usfm": "MRK 10:35",
          "end_ref": "41010045",
          "end_ref_usfm": "MRK 10:45"
        },
        {
          "start_ref": "60005001",
          "start_ref_usfm": "1PE 5:1",
          "end_ref": "60005004",
          "end_ref_usfm": "1PE 5:4"
        },
        {
          "start_ref": "46001018",
          "start_ref_usfm": "1CO 1:18",
          "end_ref": "46001031",
          "end_ref_usfm": "1CO 1:31"
        },
        {
          "start_ref": "52001006",
          "start_ref_usfm": "1TH 1:6",
          "end_ref": "52001007",
          "end_ref_usfm": "1TH 1:7"
        },
        {
          "start_ref": "47004008",
          "start_ref_usfm": "2CO 4:8",
          "end_ref": "47004012",
          "end_ref_usfm": "2CO 4:12"
        },
        {
          "start_ref": "47012008",
          "start_ref_usfm": "2CO 12:8",
          "end_ref": "47012010",
          "end_ref_usfm": "2CO 12:10"
        },
        {
          "start_ref": "55004001",
          "start_ref_usfm": "2TI 4:1",
          "end_ref": "55004005",
          "end_ref_usfm": "2TI 4:5"
        },
        {
          "start_ref": "50002003",
          "start_ref_usfm": "PHP 2:3",
          "end_ref": "50002008",
          "end_ref_usfm": "PHP 2:8"
        },
        {
          "start_ref": "55002011",
          "start_ref_usfm": "2TI 2:11",
          "end_ref": "55002012",
          "end_ref_usfm": "2TI 2:12"
        },
        {
          "start_ref": "55002010",
          "start_ref_usfm": "2TI 2:10",
          "end_ref": "55002012",
          "end_ref_usfm": "2TI 2:12"
        }
      ],
      "resource": []
    }
  }
]