[
  {
    "content_id": 709609,
    "reference_id": 203380,
    "title": "न्यायी के रूप में प्रभु का आगमन",
    "media_type": "Text",
    "index_reference": "न्यायी के रूप में प्रभु का आगमन",
    "language": "hin",
    "content": "<p>बाइबल हमें बताती है कि न्याय का एक दिन आएगा। याकूब की पुस्तक यीशु के अनुयायियों को उस दिन के बारे में एक चेतावनी और एक वादा देती है। याकूब प्रभु के भविष्य के न्यायी के रूप में आने की घोषणा करते हैं (<a href=\"https://ref.ly/Jas5:7-Jas5:9\">5:7–9</a>; देखें <a href=\"https://ref.ly/Isa26:21\">यशा 26:21</a>; <a href=\"https://ref.ly/Mic1:3\">मीका 1:3</a>)। परमेश्वर, जिन्होंने व्यवस्था दिया, वे &quot;<span>न्यायाधीश तो एक ही है, जिसे बचाने और नाश करने की सामर्थ्य है</span>&quot; (<a href=\"https://ref.ly/Jas4:12\">याकू 4:12</a>)। जो लोग यीशु मसीह का विरोध करते हैं और उनके अनुयायियों पर अत्याचार करते हैं, उन्हें गम्भीर परिणाम भुगतने होंगे (देखें <a href=\"https://ref.ly/Jas2:6-Jas2:7\">याकू 2:6–7</a>; <a href=\"https://ref.ly/Jas5:5-Jas5:6\">5:5–6</a>)।</p><p>परमेश्वर यीशु के अनुयायियों का न्याय करेंगे यदि वे ये गलत कार्य करते हैं:</p><ul><li><p>यदि वे करुणा दिखाने में असफल होते हैं (<a href=\"https://ref.ly/Jas2:13\">2:13</a>);</p></li><li><p>यदि वे संसार और इसके मूल्यों के साथ मित्रता कर लेते हैं (<a href=\"https://ref.ly/Jas4:4\">4:4</a>);</p></li><li><p>यदि वे अपने शब्दों से पाप करते हैं (<a href=\"https://ref.ly/Jas4:11\">4:11</a>; <a href=\"https://ref.ly/Jas5:9\">5:9</a>); या</p></li><li><p>यदि वे बुरी इच्छाओं को संतुष्ट करने के लिए जीवन जीते हैं (<a href=\"https://ref.ly/Jas4:1\">4:1</a>, <a href=\"https://ref.ly/Jas4:16\">16</a>)।</p></li></ul><p>परमेश्वर उनका न्याय उस व्यवस्था के अनुसार करेंगे जो उन्हें स्वतंत्र करने के लिए था (<a href=\"https://ref.ly/Jas2:12\">2:12</a>)।</p><p>प्रभु का भविष्य में आगमन हमारे वर्तमान जीवन को प्रभावित करता है। परमेश्वर पहले से ही विश्वासयोग्य दरिद्र का सम्मान करते हैं और उन अमीरों को नीचा दिखाते हैं जो उनके साथ बुरा व्यवहार करते हैं (<a href=\"https://ref.ly/Jas1:9-Jas1:10\">याकू 1:9–10</a>; <a href=\"https://ref.ly/Jas5:2-Jas5:3\">5:2–3</a>)। यीशु के अनुयायी पहले से ही परमेश्वर के विशेष लोग हैं क्योंकि परमेश्वर सभी चीजों को पुनर्स्थापित कर रहे हैं (<a href=\"https://ref.ly/Jas1:18\">1:18</a>)। याकूब कहते हैं कि हमें यीशु मसीह के राज्य के &quot;<span>राज व्यवस्था</span>&quot; का पालन करना चाहिए (<a href=\"https://ref.ly/Jas2:8\">2:8</a>)। यीशु के अनुयायी एक दिन इस राज्य के उत्तराधिकारी होंगे (<a href=\"https://ref.ly/Jas2:5\">2:5</a>)।</p><p>यीशु की वापसी तुरन्त नहीं हो सकती है। इसलिए याकूब मसीहियों को प्रोत्साहित करते हैं कि वे सहनशीलता बनाए रखें और यीशु की वापसी का धैर्यपूर्वक इंतजार करें (<a href=\"https://ref.ly/Jas1:3-Jas1:4\">याकू 1:3–4</a>; <a href=\"https://ref.ly/Jas5:7-Jas5:8\">5:7–8</a>)। वे &quot;जीवन का मुकुट&quot; प्राप्त करेंगे (<a href=\"https://ref.ly/Jas1:12\">1:12</a>)। और वे धार्मिकता के पुरस्कार प्राप्त करेंगे, जो परमेश्वर के प्रति विश्वासयोग्य जीवन से प्राप्त होते हैं (<a href=\"https://ref.ly/Jas3:18\">3:18</a>)।</p><p>चूंकि न्याय आ रहा है, याकूब यीशु के अनुयायियों को &quot;शैतान का विरोध&quot; करने और परमेश्वर के &quot;अधीन&quot; हो जाने का आदेश देते हैं (<a href=\"https://ref.ly/Jas4:7\">याकू 4:7</a>)। हमें अपने पाप पर &quot;शोक&quot; करना चाहिए और शुद्ध इरादों और कार्यों के साथ जीना चाहिए (<a href=\"https://ref.ly/Jas4:8-Jas4:9\">4:8–9</a>)। हमें हर एक मसीही भाई या बहन की सहायता करनी चाहिए जो &quot;सत्य से&quot; अनन्त मृत्यु की ओर बढ़ रहे हैं (<a href=\"https://ref.ly/Jas5:19-Jas5:20\">5:19–20</a>)। भविष्यद्वक्ता एलिय्याह की तरह, हमें विश्वास रखना चाहिए, और प्रार्थना और अंगीकार का अभ्यास करना चाहिए (<a href=\"https://ref.ly/Jas5:13-Jas5:18\">5:13–18</a>)। अय्यूब की तरह, हमें कष्ट सहना चाहिए। अन्ततः, हम परमेश्वर की दयालुता और करुणा को समझेंगे (<a href=\"https://ref.ly/Jas4:10\">4:10</a>; <a href=\"https://ref.ly/Jas5:11\">5:11</a>)।</p><p><u>आगे के अध्ययन के लिए&nbsp;अंश</u></p><p><a href=\"https://ref.ly/1Sam2:10\">1 शमूएल 2:10</a>; <a href=\"https://ref.ly/Ps2:7-Ps2:12\">भजन संहिता 2:7–12</a>; <a href=\"https://ref.ly/Ps96:11-Ps96:13\">96:11–13</a>; <a href=\"https://ref.ly/Isa26:21\">यशायाह 26:21</a>; <a href=\"https://ref.ly/Mic1:3\">मीका 1:3</a>; <a href=\"https://ref.ly/Matt16:27\">मत्ती 16:27</a>; <a href=\"https://ref.ly/Luke12:35-Luke12:48\">लूका 12:35–48</a>; <a href=\"https://ref.ly/Luke18:8\">18:8</a>; <a href=\"https://ref.ly/John5:22-John5:30\">यूहन्ना 5:22–30</a>; <a href=\"https://ref.ly/Acts10:42\">प्रेरितों के काम 10:42</a>; <a href=\"https://ref.ly/1Cor4:5\">1 कुरिन्थियों 4:5</a>; <a href=\"https://ref.ly/Jas5:7-Jas5:9\">याकूब 5:7–9</a>; <a href=\"https://ref.ly/1John2:28\">1 यूहन्ना 2:28</a></p>",
    "associations": {
      "passage": [
        {
          "start_ref": "09002010",
          "start_ref_usfm": "1SA 2:10",
          "end_ref": "09002010",
          "end_ref_usfm": "1SA 2:10"
        },
        {
          "start_ref": "23026021",
          "start_ref_usfm": "ISA 26:21",
          "end_ref": "23026021",
          "end_ref_usfm": "ISA 26:21"
        },
        {
          "start_ref": "33001003",
          "start_ref_usfm": "MIC 1:3",
          "end_ref": "33001003",
          "end_ref_usfm": "MIC 1:3"
        },
        {
          "start_ref": "40016027",
          "start_ref_usfm": "MAT 16:27",
          "end_ref": "40016027",
          "end_ref_usfm": "MAT 16:27"
        },
        {
          "start_ref": "42018008",
          "start_ref_usfm": "LUK 18:8",
          "end_ref": "42018008",
          "end_ref_usfm": "LUK 18:8"
        },
        {
          "start_ref": "44010042",
          "start_ref_usfm": "ACT 10:42",
          "end_ref": "44010042",
          "end_ref_usfm": "ACT 10:42"
        },
        {
          "start_ref": "46004005",
          "start_ref_usfm": "1CO 4:5",
          "end_ref": "46004005",
          "end_ref_usfm": "1CO 4:5"
        },
        {
          "start_ref": "59001012",
          "start_ref_usfm": "JAS 1:12",
          "end_ref": "59001012",
          "end_ref_usfm": "JAS 1:12"
        },
        {
          "start_ref": "59001018",
          "start_ref_usfm": "JAS 1:18",
          "end_ref": "59001018",
          "end_ref_usfm": "JAS 1:18"
        },
        {
          "start_ref": "59002005",
          "start_ref_usfm": "JAS 2:5",
          "end_ref": "59002005",
          "end_ref_usfm": "JAS 2:5"
        },
        {
          "start_ref": "59002008",
          "start_ref_usfm": "JAS 2:8",
          "end_ref": "59002008",
          "end_ref_usfm": "JAS 2:8"
        },
        {
          "start_ref": "59002012",
          "start_ref_usfm": "JAS 2:12",
          "end_ref": "59002012",
          "end_ref_usfm": "JAS 2:12"
        },
        {
          "start_ref": "59002013",
          "start_ref_usfm": "JAS 2:13",
          "end_ref": "59002013",
          "end_ref_usfm": "JAS 2:13"
        },
        {
          "start_ref": "59003018",
          "start_ref_usfm": "JAS 3:18",
          "end_ref": "59003018",
          "end_ref_usfm": "JAS 3:18"
        },
        {
          "start_ref": "59004001",
          "start_ref_usfm": "JAS 4:1",
          "end_ref": "59004001",
          "end_ref_usfm": "JAS 4:1"
        },
        {
          "start_ref": "59004004",
          "start_ref_usfm": "JAS 4:4",
          "end_ref": "59004004",
          "end_ref_usfm": "JAS 4:4"
        },
        {
          "start_ref": "59004007",
          "start_ref_usfm": "JAS 4:7",
          "end_ref": "59004007",
          "end_ref_usfm": "JAS 4:7"
        },
        {
          "start_ref": "59004010",
          "start_ref_usfm": "JAS 4:10",
          "end_ref": "59004010",
          "end_ref_usfm": "JAS 4:10"
        },
        {
          "start_ref": "59004011",
          "start_ref_usfm": "JAS 4:11",
          "end_ref": "59004011",
          "end_ref_usfm": "JAS 4:11"
        },
        {
          "start_ref": "59004012",
          "start_ref_usfm": "JAS 4:12",
          "end_ref": "59004012",
          "end_ref_usfm": "JAS 4:12"
        },
        {
          "start_ref": "59004016",
          "start_ref_usfm": "JAS 4:16",
          "end_ref": "59004016",
          "end_ref_usfm": "JAS 4:16"
        },
        {
          "start_ref": "59005009",
          "start_ref_usfm": "JAS 5:9",
          "end_ref": "59005009",
          "end_ref_usfm": "JAS 5:9"
        },
        {
          "start_ref": "59005011",
          "start_ref_usfm": "JAS 5:11",
          "end_ref": "59005011",
          "end_ref_usfm": "JAS 5:11"
        },
        {
          "start_ref": "62002028",
          "start_ref_usfm": "1JN 2:28",
          "end_ref": "62002028",
          "end_ref_usfm": "1JN 2:28"
        },
        {
          "start_ref": "59005019",
          "start_ref_usfm": "JAS 5:19",
          "end_ref": "59005020",
          "end_ref_usfm": "JAS 5:20"
        },
        {
          "start_ref": "59005013",
          "start_ref_usfm": "JAS 5:13",
          "end_ref": "59005018",
          "end_ref_usfm": "JAS 5:18"
        },
        {
          "start_ref": "59005007",
          "start_ref_usfm": "JAS 5:7",
          "end_ref": "59005008",
          "end_ref_usfm": "JAS 5:8"
        },
        {
          "start_ref": "42012035",
          "start_ref_usfm": "LUK 12:35",
          "end_ref": "42012048",
          "end_ref_usfm": "LUK 12:48"
        },
        {
          "start_ref": "19096011",
          "start_ref_usfm": "PSA 96:11",
          "end_ref": "19096013",
          "end_ref_usfm": "PSA 96:13"
        },
        {
          "start_ref": "59002006",
          "start_ref_usfm": "JAS 2:6",
          "end_ref": "59002007",
          "end_ref_usfm": "JAS 2:7"
        },
        {
          "start_ref": "59005007",
          "start_ref_usfm": "JAS 5:7",
          "end_ref": "59005009",
          "end_ref_usfm": "JAS 5:9"
        },
        {
          "start_ref": "59005005",
          "start_ref_usfm": "JAS 5:5",
          "end_ref": "59005006",
          "end_ref_usfm": "JAS 5:6"
        },
        {
          "start_ref": "59001009",
          "start_ref_usfm": "JAS 1:9",
          "end_ref": "59001010",
          "end_ref_usfm": "JAS 1:10"
        },
        {
          "start_ref": "59005002",
          "start_ref_usfm": "JAS 5:2",
          "end_ref": "59005003",
          "end_ref_usfm": "JAS 5:3"
        },
        {
          "start_ref": "59001003",
          "start_ref_usfm": "JAS 1:3",
          "end_ref": "59001004",
          "end_ref_usfm": "JAS 1:4"
        },
        {
          "start_ref": "59004008",
          "start_ref_usfm": "JAS 4:8",
          "end_ref": "59004009",
          "end_ref_usfm": "JAS 4:9"
        },
        {
          "start_ref": "19002007",
          "start_ref_usfm": "PSA 2:7",
          "end_ref": "19002012",
          "end_ref_usfm": "PSA 2:12"
        },
        {
          "start_ref": "43005022",
          "start_ref_usfm": "JHN 5:22",
          "end_ref": "43005030",
          "end_ref_usfm": "JHN 5:30"
        }
      ],
      "resource": []
    }
  }
]