[
  {
    "content_id": 709548,
    "reference_id": 203319,
    "title": "क्रूस और फसह",
    "media_type": "Text",
    "index_reference": "क्रूस और फसह",
    "language": "hin",
    "content": "<p>यूहन्ना के सुसमाचार की शुरुआत में, यूहन्ना बपतिस्मा देने वाले ने यीशु को &quot;परमेश्वर का मेमना&quot; के रूप में प्रस्तुत किया (<a href=\"https://ref.ly/John1:29\">यूह 1:29</a>, <a href=\"https://ref.ly/John1:36\">36</a>)। यह वाक्यांश प्रतिदिन मन्दिर में बलिदान किए जाने वाले मेमने का सन्दर्भ हो सकता है (<a href=\"https://ref.ly/Exod29:38-Exod29:46\">निर्ग 29:38–46</a>)। या यह <a href=\"https://ref.ly/Isa53:7\">यशा 53:7</a> में वर्णित बलिदान के मेमने को संदर्भित कर सकता है (देखें <a href=\"https://ref.ly/Acts8:32-Acts8:35\">प्रेरि 8:32–35</a>; <a href=\"https://ref.ly/Rev5:5-Rev5:14\">प्रका 5:5–14</a>)। दोनों बलिदान पाप से उद्धार और क्षमा का प्रतिनिधित्व करते हैं।</p><p>फिर भी, यह सब प्रेरित यूहन्ना का उद्देश्य नहीं था। यूहन्ना ने यीशु को फसह के मेमने के रूप में प्रस्तुत किया। इस मेमने की मृत्यु फसह के समय की केन्द्रीय घटना है (देखें <a href=\"https://ref.ly/Exod12:43-Exod12:47\">निर्ग 12:43–47</a>; <a href=\"https://ref.ly/Luke22:7\">लूका 22:7</a>; <a href=\"https://ref.ly/1Cor5:7\">1 कुरि 5:7</a>)।</p><p>पहली सदी में, यहूदी हर वसन्त में यरूशलेम की यात्रा करते थे ताकि फसह का उत्सव मना सकें और एक बार फिर से मिस्र से निर्गमन की कहानी पढ़ सकें (देखें <a href=\"https://ref.ly/Exod12:1-Exod15:27\">निर्ग 12–15</a>)। जब परमेश्वर ने इस्राएलियों को मिस्र से बचाया, तो उन्होंने अपने दरवाजों पर मेमने का लहू लगाया था। इस कार्य ने प्रत्येक घर के अन्दर रहने वालों को मृत्यु से बचाया (<a href=\"https://ref.ly/Exod12:1-Exod12:51\">निर्ग 12</a>)। जो यहूदी फसह के लिए यरूशलेम आते थे, उन्हें बलिदान के लिए एक निर्दोष युवा मेमना देना होता था। मेमने में कोई बीमारी या टूटी हड्डियाँ नहीं होनी चाहिए।</p><p>यीशु ने अपने अन्तिम फसह भोजन का उपयोग यह दिखाने के लिए किया कि उनकी बलिदानी मृत्यु इस पर्व को नया अर्थ देगी (<a href=\"https://ref.ly/Mark14:17-Mark14:25\">मर 14:17–25</a>)। उनके क्रूसीकरण पर, उन्होंने यीशु के पैर नहीं तोड़ें, जो अक्सर फसह नियम को पूरा करने के लिए किया जाता था (<a href=\"https://ref.ly/John19:31-John19:33\">यूह 19:31–33</a>; देखें <a href=\"https://ref.ly/Exod12:46\">निर्ग 12:46</a>)। उसके घावों से लहू बहता गया (<a href=\"https://ref.ly/John19:34\">यूह 19:34</a>)। इससे यह दिखाया गया कि वे दूसरों के लिए अपना जीवन दे रहे थे। मिस्र में फसह के दौरान यहूदियों के परिवारों को बचाने के लिए एक मेमना मरा था। इसी प्रकार, परमेश्वर के पुत्र की क्रूस पर मृत्यु संसार में उद्धार को लाती है।</p><p><u>अधिक अध्ययन के लिए&nbsp;पद्द्यांश</u></p><p><a href=\"https://ref.ly/Exod12:1-Exod13:16\">निर्गमन 12:1–13:16</a>; <a href=\"https://ref.ly/Exod29:38-Exod29:46\">29:38–46</a>; <a href=\"https://ref.ly/Num9:1-Num9:14\">गिनती 9:1–14</a>; <a href=\"https://ref.ly/Deut16:1-Deut16:8\">व्यवस्थाविवरण 16:1–8</a>; <a href=\"https://ref.ly/2Kgs23:21-2Kgs23:23\">2 राजाओं 23:21–23</a>; <a href=\"https://ref.ly/2Chr30:1-2Chr30:27\">2 इतिहास 30:1–27</a>; <a href=\"https://ref.ly/Ezra6:19-Ezra6:21\">एज्रा 6:19–21</a>; <a href=\"https://ref.ly/Isa53:7\">यशायाह 53:7</a>; <a href=\"https://ref.ly/Ezek45:21-Ezek45:22\">यहेजकेल 45:21–22</a>; <a href=\"https://ref.ly/Matt26:2\">मत्ती 26:2</a>, <a href=\"https://ref.ly/Matt26:17-Matt26:19\">17–19</a>; <a href=\"https://ref.ly/Mark14:17-Mark14:31\">मरकुस 14:17–31</a>; <a href=\"https://ref.ly/Luke22:14-Luke22:30\">लूका 22:14–30</a>; <a href=\"https://ref.ly/John1:29\">यूहन्ना 1:29</a>, <a href=\"https://ref.ly/John1:36\">36</a>; <a href=\"https://ref.ly/John19:17-John19:36\">यूहन्ना 19:17–36</a>; <a href=\"https://ref.ly/Acts8:32-Acts8:35\">प्रेरितों के काम 8:32–35</a>; <a href=\"https://ref.ly/Acts12:3-Acts12:4\">12:3–4</a>; <a href=\"https://ref.ly/1Cor5:7-1Cor5:8\">1 कुरिन्थियों 5:7–8</a>; <a href=\"https://ref.ly/Heb11:28\">इब्रानियों 11:28</a>; <a href=\"https://ref.ly/Rev5:5-Rev5:14\">प्रकाशितवाक्य 5:5–14</a></p>",
    "associations": {
      "passage": [
        {
          "start_ref": "02012046",
          "start_ref_usfm": "EXO 12:46",
          "end_ref": "02012046",
          "end_ref_usfm": "EXO 12:46"
        },
        {
          "start_ref": "23053007",
          "start_ref_usfm": "ISA 53:7",
          "end_ref": "23053007",
          "end_ref_usfm": "ISA 53:7"
        },
        {
          "start_ref": "40026002",
          "start_ref_usfm": "MAT 26:2",
          "end_ref": "40026002",
          "end_ref_usfm": "MAT 26:2"
        },
        {
          "start_ref": "42022007",
          "start_ref_usfm": "LUK 22:7",
          "end_ref": "42022007",
          "end_ref_usfm": "LUK 22:7"
        },
        {
          "start_ref": "43001029",
          "start_ref_usfm": "JHN 1:29",
          "end_ref": "43001029",
          "end_ref_usfm": "JHN 1:29"
        },
        {
          "start_ref": "43001036",
          "start_ref_usfm": "JHN 1:36",
          "end_ref": "43001036",
          "end_ref_usfm": "JHN 1:36"
        },
        {
          "start_ref": "43019034",
          "start_ref_usfm": "JHN 19:34",
          "end_ref": "43019034",
          "end_ref_usfm": "JHN 19:34"
        },
        {
          "start_ref": "46005007",
          "start_ref_usfm": "1CO 5:7",
          "end_ref": "46005007",
          "end_ref_usfm": "1CO 5:7"
        },
        {
          "start_ref": "58011028",
          "start_ref_usfm": "HEB 11:28",
          "end_ref": "58011028",
          "end_ref_usfm": "HEB 11:28"
        },
        {
          "start_ref": "44008032",
          "start_ref_usfm": "ACT 8:32",
          "end_ref": "44008035",
          "end_ref_usfm": "ACT 8:35"
        },
        {
          "start_ref": "02012001",
          "start_ref_usfm": "EXO 12:1",
          "end_ref": "02015027",
          "end_ref_usfm": "EXO 15:27"
        },
        {
          "start_ref": "12023021",
          "start_ref_usfm": "2KI 23:21",
          "end_ref": "12023023",
          "end_ref_usfm": "2KI 23:23"
        },
        {
          "start_ref": "46005007",
          "start_ref_usfm": "1CO 5:7",
          "end_ref": "46005008",
          "end_ref_usfm": "1CO 5:8"
        },
        {
          "start_ref": "14030001",
          "start_ref_usfm": "2CH 30:1",
          "end_ref": "14030027",
          "end_ref_usfm": "2CH 30:27"
        },
        {
          "start_ref": "05016001",
          "start_ref_usfm": "DEU 16:1",
          "end_ref": "05016008",
          "end_ref_usfm": "DEU 16:8"
        },
        {
          "start_ref": "02012001",
          "start_ref_usfm": "EXO 12:1",
          "end_ref": "02012051",
          "end_ref_usfm": "EXO 12:51"
        },
        {
          "start_ref": "41014017",
          "start_ref_usfm": "MRK 14:17",
          "end_ref": "41014025",
          "end_ref_usfm": "MRK 14:25"
        },
        {
          "start_ref": "43019031",
          "start_ref_usfm": "JHN 19:31",
          "end_ref": "43019033",
          "end_ref_usfm": "JHN 19:33"
        },
        {
          "start_ref": "04009001",
          "start_ref_usfm": "NUM 9:1",
          "end_ref": "04009014",
          "end_ref_usfm": "NUM 9:14"
        },
        {
          "start_ref": "44012003",
          "start_ref_usfm": "ACT 12:3",
          "end_ref": "44012004",
          "end_ref_usfm": "ACT 12:4"
        },
        {
          "start_ref": "02029038",
          "start_ref_usfm": "EXO 29:38",
          "end_ref": "02029046",
          "end_ref_usfm": "EXO 29:46"
        },
        {
          "start_ref": "02012001",
          "start_ref_usfm": "EXO 12:1",
          "end_ref": "02013016",
          "end_ref_usfm": "EXO 13:16"
        },
        {
          "start_ref": "66005005",
          "start_ref_usfm": "REV 5:5",
          "end_ref": "66005014",
          "end_ref_usfm": "REV 5:14"
        },
        {
          "start_ref": "02012043",
          "start_ref_usfm": "EXO 12:43",
          "end_ref": "02012047",
          "end_ref_usfm": "EXO 12:47"
        },
        {
          "start_ref": "15006019",
          "start_ref_usfm": "EZR 6:19",
          "end_ref": "15006021",
          "end_ref_usfm": "EZR 6:21"
        },
        {
          "start_ref": "26045021",
          "start_ref_usfm": "EZK 45:21",
          "end_ref": "26045022",
          "end_ref_usfm": "EZK 45:22"
        },
        {
          "start_ref": "40026017",
          "start_ref_usfm": "MAT 26:17",
          "end_ref": "40026019",
          "end_ref_usfm": "MAT 26:19"
        },
        {
          "start_ref": "41014017",
          "start_ref_usfm": "MRK 14:17",
          "end_ref": "41014031",
          "end_ref_usfm": "MRK 14:31"
        },
        {
          "start_ref": "42022014",
          "start_ref_usfm": "LUK 22:14",
          "end_ref": "42022030",
          "end_ref_usfm": "LUK 22:30"
        },
        {
          "start_ref": "43019017",
          "start_ref_usfm": "JHN 19:17",
          "end_ref": "43019036",
          "end_ref_usfm": "JHN 19:36"
        }
      ],
      "resource": []
    }
  }
]