[
  {
    "content_id": 709586,
    "reference_id": 203357,
    "title": "पुराना जीवन और नया जीवन",
    "media_type": "Text",
    "index_reference": "पुराना जीवन और नया जीवन",
    "language": "hin",
    "content": "<p>जब लोग मसीही बनते हैं, तो वे यीशु के साथ एक हो जाते हैं और उनकी मृत्यु तथा पुनरुत्थान में सहभागी हो जाते हैं। उनका पुराना जीवन, जो पाप से चिन्हित था, यीशु के साथ आने से समाप्त हो जाता है। वे अपने अन्दर उनकी कार्य करने वाली शक्ति के द्वारा एक नया जीवन आरम्भ करते हैं (देखें <a href=\"https://ref.ly/Rom6:3-Rom6:14\">रोम 6:3–14</a>)।</p><p>परमेश्वर उन्हें अपने आत्मा के द्वारा रूपान्तरित करते हैं। उनकी बुद्धि नई बन जाती है (देखें <a href=\"https://ref.ly/Rom12:2\">रोम 12:2</a>)। उनकी इच्छाएँ और कार्य बदल जाते हैं और उनका जीवन उनके आत्मा के फल को प्रगट करने लगता है (<a href=\"https://ref.ly/Gal5:22-Gal5:23\">गला 5:22–23</a>)। वे आत्मिक रूप से बढ़ने लगते हैं और यीशु के समान बनने लगते हैं।</p><p>मसीहियों का यह कर्तव्य है कि वे यीशु की मृत्यु और पुनरुत्थान की &quot;समानता&quot; में बनें (देखें <a href=\"https://ref.ly/Phil3:10-Phil3:11\">फिलि 3:10–14</a>)। उन्हें अन्धकार से मुड़कर एक ऐसे जीवन के लिए समर्पित होना चाहिए जो ज्योति से परिपूर्ण हो (<a href=\"https://ref.ly/Eph4:17-Eph5:20\">इफि 4:17–5:20</a>)। इसका अर्थ है कि उन्हें बुराई के जीवन को छोड़कर परमेश्वर के भले मार्गों में चलना चाहिए। प्रेरित पौलुस इस परिवर्तन को वस्त्रों की छवि के माध्यम से वर्णित करते हैं। परमेश्वर मसीहियों को बुलाता है कि वे पुराने, पापमय जीवन को, जो शैतान के प्रभाव में था, उतार फेंकें और एक नया, पवित्र जीवन पहन लें जो पवित्र आत्मा के मार्गदर्शन में हो (<a href=\"https://ref.ly/Eph4:21-Eph4:24\">इफि 4:21–24</a>; <a href=\"https://ref.ly/Col3:1-Col3:15\">कुल 3:1–15</a>; देखें <a href=\"https://ref.ly/Gal3:27\">गला 3:27</a>)। ऐसा करते हुए, वे परमेश्वर के अनुग्रह और शक्ति पर अपनी निर्भरता को स्वीकार करते हैं।</p><p><u>अधिक अध्ययन के लिए अंश</u></p><p><a href=\"https://ref.ly/Rom6:3-Rom6:14\">रोमियों 6:3–14</a>; <a href=\"https://ref.ly/Rom12:1-Rom12:2\">12:1–2</a>; <a href=\"https://ref.ly/Gal5:19-Gal5:23\">गलातियों 5:19–23</a>; <a href=\"https://ref.ly/Eph4:17-Eph5:20\">इफिसियों 4:17–5:20</a>; <a href=\"https://ref.ly/Phil3:12-Phil3:13\">फिलिप्पियों 3:12–14</a></p>",
    "associations": {
      "passage": [
        {
          "start_ref": "45012002",
          "start_ref_usfm": "ROM 12:2",
          "end_ref": "45012002",
          "end_ref_usfm": "ROM 12:2"
        },
        {
          "start_ref": "48003027",
          "start_ref_usfm": "GAL 3:27",
          "end_ref": "48003027",
          "end_ref_usfm": "GAL 3:27"
        },
        {
          "start_ref": "50003010",
          "start_ref_usfm": "PHP 3:10",
          "end_ref": "50003011",
          "end_ref_usfm": "PHP 3:11"
        },
        {
          "start_ref": "45012001",
          "start_ref_usfm": "ROM 12:1",
          "end_ref": "45012002",
          "end_ref_usfm": "ROM 12:2"
        },
        {
          "start_ref": "48005022",
          "start_ref_usfm": "GAL 5:22",
          "end_ref": "48005023",
          "end_ref_usfm": "GAL 5:23"
        },
        {
          "start_ref": "48005019",
          "start_ref_usfm": "GAL 5:19",
          "end_ref": "48005023",
          "end_ref_usfm": "GAL 5:23"
        },
        {
          "start_ref": "49004017",
          "start_ref_usfm": "EPH 4:17",
          "end_ref": "49005020",
          "end_ref_usfm": "EPH 5:20"
        },
        {
          "start_ref": "45006003",
          "start_ref_usfm": "ROM 6:3",
          "end_ref": "45006014",
          "end_ref_usfm": "ROM 6:14"
        },
        {
          "start_ref": "49004021",
          "start_ref_usfm": "EPH 4:21",
          "end_ref": "49004024",
          "end_ref_usfm": "EPH 4:24"
        },
        {
          "start_ref": "51003001",
          "start_ref_usfm": "COL 3:1",
          "end_ref": "51003015",
          "end_ref_usfm": "COL 3:15"
        },
        {
          "start_ref": "50003012",
          "start_ref_usfm": "PHP 3:12",
          "end_ref": "50003013",
          "end_ref_usfm": "PHP 3:13"
        }
      ],
      "resource": []
    }
  }
]